ssb_libtest44/__init__.py
ssb_libtest44/__main__.py
ssb_libtest44/functions.py
ssb_libtest44/py.typed
ssb_libtest44-0.0.1.dist-info/LICENSE
ssb_libtest44-0.0.1.dist-info/METADATA
ssb_libtest44-0.0.1.dist-info/WHEEL
ssb_libtest44-0.0.1.dist-info/entry_points.txt
ssb_libtest44-0.0.1.dist-info/RECORD
